fast_scores/__init__.py
fast_scores/__main__.py
fast_scores/cos_matrix2.py
fast_scores/en2zh.py
fast_scores/fast_scores.pyc
fast_scores/gen_cmat.py
fast_scores/gen_model.py
fast_scores/insert_spaces.py
fast_scores/loadtext.py
fast_scores/mdx_dict_e2c.lzma
fast_scores/process_en.pyc
fast_scores/process_zh.pyc
fast_scores/split_chinese.py
fast_scores/tk_plot.py
fast_scores/word_tr.pyc
LICENSE
fast_scores-0.1.4.dist-info/LICENSE
fast_scores-0.1.4.dist-info/METADATA
fast_scores-0.1.4.dist-info/WHEEL
fast_scores-0.1.4.dist-info/RECORD
