Metadata-Version: 2.1
Name: fast-scores
Version: 0.1.4
Summary:  
Home-page: https://github.com/ffreemt/fast-scores
License: MIT
Author: freemt
Requires-Python: >=3.8,<4.0
Classifier: License :: OSI Approved :: MIT License
Classifier: Programming Language :: Python :: 3
Classifier: Programming Language :: Python :: 3.8
Classifier: Programming Language :: Python :: 3.9
Classifier: Programming Language :: Python :: 3.10
Classifier: Programming Language :: Python :: 3.11
Classifier: Programming Language :: Python :: 3.12
Requires-Dist: cchardet (>=2.1.7,<3.0.0)
Requires-Dist: fastlid (>=0.1.9,<0.2.0)
Requires-Dist: joblib (>=1.0.1,<2.0.0)
Requires-Dist: logzero (>=1.7.0,<2.0.0)
Requires-Dist: msgpack (>=1.0.2,<2.0.0)
Requires-Dist: nltk (>=3.6.2,<4.0.0)
Requires-Dist: numpy (>=1.21.0,<2.0.0)
Requires-Dist: scikit-learn (>=1.2.0,<2.0.0)
Requires-Dist: simplemma (>=0.3.0,<0.4.0)
Project-URL: Repository, https://github.com/ffreemt/fast-scores
